{
  "$id": "ce_faculty",
  "$schema": "https://schema.yext.com/config/km/entity-type/v1",
  "description": "",
  "displayName": "Faculty",
  "enabled": true,
  "field": [
    {
      "id": "landingPageUrl",
      "required": false
    },
    {
      "id": "description",
      "required": false
    },
    {
      "id": "name",
      "required": true
    },
    {
      "id": "c_activeInAnswers",
      "required": false
    },
    {
      "id": "c_areasOfInterest",
      "required": false
    },
    {
      "id": "c_associatedAcademicPrograms",
      "required": false
    },
    {
      "id": "c_degree",
      "required": false
    },
    {
      "id": "c_discipline",
      "required": false
    },
    {
      "id": "c_educationInstitution",
      "required": false
    },
    {
      "id": "keywords",
      "required": false
    },
    {
      "id": "c_photo",
      "required": false
    },
    {
      "id": "c_primaryCTA",
      "required": false
    },
    {
      "id": "c_research",
      "required": false
    },
    {
      "id": "c_secondaryCTA",
      "required": false
    },
    {
      "id": "c_title",
      "required": false
    },
    {
      "id": "emails",
      "required": false
    },
    {
      "id": "firstName",
      "required": false
    },
    {
      "id": "folder",
      "required": false
    },
    {
      "id": "headshot",
      "required": false
    },
    {
      "id": "labels",
      "required": false
    },
    {
      "id": "lastName",
      "required": false
    },
    {
      "id": "mainPhone",
      "required": false
    },
    {
      "id": "middleName",
      "required": false
    },
    {
      "id": "entityId",
      "required": true
    }
  ],
  "pluralDisplayName": ""
}